lightning_attn/__init__.py
lightning_attn/ops/__init__.py
lightning_attn/ops/lightning_attn_interface.py
lightning_attn/ops/torch/__init__.py
lightning_attn/ops/torch/linear_attention.py
lightning_attn/ops/torch/srmsnorm.py
lightning_attn/ops/triton/__init__.py
lightning_attn/ops/triton/lightning_attn2.py
lightning_attn/ops/triton/lightning_attn2_no_decay.py
lightning_attn/ops/triton/srmsnorm.py
lightning_attn/utils/__init__.py
lightning_attn/utils/utils.py
lightning_attn-0.0.5.dist-info/LICENSE
lightning_attn-0.0.5.dist-info/METADATA
lightning_attn-0.0.5.dist-info/WHEEL
lightning_attn-0.0.5.dist-info/top_level.txt
lightning_attn-0.0.5.dist-info/RECORD
