Metadata-Version: 2.1
Name: lightning-attn
Version: 0.0.5
Author: Doraemonzzz
License-File: LICENSE
Requires-Dist: torch
Requires-Dist: einops
Requires-Dist: triton
